ding0/__init__.py
ding0/config/__init__.py
ding0/config/config_calc.cfg
ding0/config/config_db_interfaces.py
ding0/config/config_db_tables.cfg
ding0/config/config_files.cfg
ding0/config/config_misc.cfg
ding0/core/__init__.py
ding0/core/network/__init__.py
ding0/core/network/cable_distributors.py
ding0/core/network/grids.py
ding0/core/network/loads.py
ding0/core/network/stations.py
ding0/core/network/transformers.py
ding0/core/powerflow/__init__.py
ding0/core/structure/__init__.py
ding0/core/structure/groups.py
ding0/core/structure/regions.py
ding0/data/equipment-parameters_LV_cables.csv
ding0/data/equipment-parameters_LV_transformers.csv
ding0/data/equipment-parameters_MV_cables.csv
ding0/data/equipment-parameters_MV_overhead_lines.csv
ding0/data/equipment-parameters_MV_transformers.csv
ding0/data/model_grids-lv_relation_apartment_string.csv
ding0/data/model_grids-lv_string_properties.csv
ding0/flexopt/__init__.py
ding0/flexopt/check_tech_constraints.py
ding0/flexopt/reinforce_grid.py
ding0/flexopt/reinforce_measures.py
ding0/flexopt/reinforce_measures_dena.py
ding0/grid/__init__.py
ding0/grid/tools.py
ding0/grid/lv_grid/__init__.py
ding0/grid/lv_grid/build_grid.py
ding0/grid/lv_grid/check.py
ding0/grid/lv_grid/lv_connect.py
ding0/grid/mv_grid/__init__.py
ding0/grid/mv_grid/mv_connect.py
ding0/grid/mv_grid/mv_routing.py
ding0/grid/mv_grid/tools.py
ding0/grid/mv_grid/models/__init__.py
ding0/grid/mv_grid/models/models.py
ding0/grid/mv_grid/solvers/__init__.py
ding0/grid/mv_grid/solvers/base.py
ding0/grid/mv_grid/solvers/local_search.py
ding0/grid/mv_grid/solvers/savings.py
ding0/grid/mv_grid/tests/__init__.py
ding0/grid/mv_grid/tests/run_test_case.py
ding0/grid/mv_grid/tests/testcases/Example-k2.vrp
ding0/grid/mv_grid/tests/testcases/Example-k3.vrp
ding0/grid/mv_grid/tests/testcases/Example-n5-k2.vrp
ding0/grid/mv_grid/tests/testcases/Augerat/A-n32-k5.vrp
ding0/grid/mv_grid/tests/testcases/Augerat/A-n33-k5.vrp
ding0/grid/mv_grid/tests/testcases/Augerat/A-n33-k6.vrp
ding0-0.2.1.dist-info/LICENSE
ding0-0.2.1.dist-info/METADATA
ding0-0.2.1.dist-info/WHEEL
ding0-0.2.1.dist-info/top_level.txt
ding0-0.2.1.dist-info/RECORD
