Metadata-Version: 2.1
Name: ding0
Version: 0.2.1
Summary: DIstribution Network GeneratOr
Home-page: https://github.com/openego/ding0
Author: Reiner Lemoine Institut
Author-email: jonathan.amme@rl-institut.de
License: GNU AGPLv3
Platform: UNKNOWN
Classifier: Development Status :: 3 - Alpha
Classifier: Environment :: Console
Classifier: Intended Audience :: Science/Research
Classifier: License :: OSI Approved :: GNU Affero General Public License v3
Classifier: Natural Language :: English
Classifier: Operating System :: POSIX :: Linux
Classifier: Operating System :: Microsoft :: Windows
Classifier: Programming Language :: Python :: 3.8
Classifier: Topic :: Scientific/Engineering
License-File: LICENSE
Requires-Dist: networkx (==2.5.1)
Requires-Dist: geopy (==2.1.0)
Requires-Dist: pandas (==1.2.4)
Requires-Dist: pyproj (==3.0.1)
Requires-Dist: sqlalchemy (<=1.3.24)
Requires-Dist: geoalchemy2 (==0.6.3)
Requires-Dist: matplotlib (<=3.4.2,>=1.5.3)
Requires-Dist: egoio (==0.4.8)
Requires-Dist: shapely (==1.7.1)
Requires-Dist: pypsa (<=0.17.1,>=0.11.0)
Requires-Dist: seaborn (==0.11.1)
Requires-Dist: unittest2 (==1.1.0)
Requires-Dist: oedialect (==0.0.10)
Requires-Dist: geopandas (==0.9.0)
Requires-Dist: descartes (==1.1.0)
Provides-Extra: dev
Requires-Dist: pytest ; extra == 'dev'
Requires-Dist: pytest-dependency ; extra == 'dev'
Requires-Dist: pytest-parallel ; extra == 'dev'
Requires-Dist: sphinx ; extra == 'dev'
Requires-Dist: sphinx-rtd-theme ; extra == 'dev'
